md2docx/__init__.py
md2docx/version.json
md2docx/bin/__init__.py
md2docx/bin/main.py
md2docx/core/__init__.py
md2docx/core/converter.py
md2docx/core/line_type.py
md2docx/core/processors/__init__.py
md2docx/core/processors/code.py
md2docx/core/processors/heading.py
md2docx/core/processors/image.py
md2docx/core/processors/list_item.py
md2docx/core/processors/paragraph.py
md2docx/core/processors/preprocess.py
md2docx/core/processors/quote.py
md2docx/core/processors/table.py
md2docx/utils/__init__.py
md2docx/utils/color.py
md2docx/utils/image.py
md2docx/utils/mermaid.py
md2docx/utils/styles.py
python_md2docx-1.0.3.dist-info/METADATA
python_md2docx-1.0.3.dist-info/WHEEL
python_md2docx-1.0.3.dist-info/entry_points.txt
python_md2docx-1.0.3.dist-info/top_level.txt
python_md2docx-1.0.3.dist-info/RECORD
